pdf_oralia/__init__.py
pdf_oralia/extract.py
pdf_oralia/join.py
pdf_oralia/pages/__init__.py
pdf_oralia/pages/charge.py
pdf_oralia/pages/locataire.py
pdf_oralia/pages/patrimoine.py
pdf_oralia/pages/recapitulatif.py
pdf_oralia/scripts.py
pdf_oralia-0.4.1.dist-info/METADATA
pdf_oralia-0.4.1.dist-info/WHEEL
pdf_oralia-0.4.1.dist-info/entry_points.txt
pdf_oralia-0.4.1.dist-info/RECORD
