Metadata-Version: 2.3
Name: pdf-oralia
Version: 0.4.1
Summary: 
Author: Bertrand Benjamin
Author-email: benjamin.bertrand@opytex.org
Requires-Python: >=3.10,<4.0
Classifier: Programming Language :: Python :: 3
Classifier: Programming Language :: Python :: 3.10
Classifier: Programming Language :: Python :: 3.11
Classifier: Programming Language :: Python :: 3.12
Classifier: Programming Language :: Python :: 3.13
Requires-Dist: click (>=8.1.3,<9.0.0)
Requires-Dist: openpyxl (>=3.0.10,<4.0.0)
Requires-Dist: pandas (>=2.2.3,<3.0.0)
Requires-Dist: pdfplumber (>=0.7.4,<0.8.0)
